mercuryFramework/__init__.py
mercuryFramework/class_calculation.py
mercuryFramework/trader.py
mercuryframework-0.1.8.dist-info/licenses/LICENSE
mercuryframework-0.1.8.dist-info/METADATA
mercuryframework-0.1.8.dist-info/WHEEL
mercuryframework-0.1.8.dist-info/top_level.txt
mercuryframework-0.1.8.dist-info/RECORD
