Metadata-Version: 2.4
Name: mercuryFramework
Version: 0.1.8
Summary: A simple quantitative finance package for algorithmic trading and financial analysis framework.
Author: Anas Arkawi
License: Mozilla Public License Version 2.0
Project-URL: Homepage, https://github.com/anasarkawi1/mercury
Project-URL: Issues, https://github.com/anasarkawi1/mercury/issues
Classifier: Programming Language :: Python :: 3
Classifier: License :: OSI Approved :: Mozilla Public License 2.0 (MPL 2.0)
Classifier: Operating System :: OS Independent
Classifier: Intended Audience :: Financial and Insurance Industry
Classifier: Intended Audience :: Science/Research
Classifier: Intended Audience :: Developers
Classifier: Topic :: Office/Business :: Financial
Classifier: Topic :: Office/Business :: Financial :: Investment
Classifier: Topic :: Scientific/Engineering
Classifier: Development Status :: 4 - Beta
Requires-Python: >=3.11
License-File: LICENSE
Requires-Dist: numpy
Requires-Dist: pandas
Requires-Dist: binance-connector
Requires-Dist: dataclasses
Requires-Dist: hermesConnector==0.0.9
Dynamic: license-file
